foyeshow.py
foyeshow-0.0.1.dist-info/METADATA
foyeshow-0.0.1.dist-info/WHEEL
foyeshow-0.0.1.dist-info/top_level.txt
foyeshow-0.0.1.dist-info/RECORD
