Metadata-Version: 2.1
Name: foyeshow
Version: 0.0.1
Summary: A small toy that replaces OpenCV's imshow combination with pure Python implementation
Author: foye
Author-email: 845903926@qq.com
Classifier: Programming Language :: Python :: 3
Classifier: License :: OSI Approved :: MIT License
Classifier: Operating System :: Microsoft :: Windows
Requires-Python: >=3.11.4
Requires-Dist: numpy (>=1.20.0)
